pyalign-0.4.4.dist-info/top_level.txt
pyalign-0.4.4.dist-info/METADATA
pyalign-0.4.4.dist-info/LICENSE
pyalign-0.4.4.dist-info/RECORD
pyalign-0.4.4.dist-info/WHEEL
pyalign/simple.py
pyalign/__init__.py
pyalign/utils.py
pyalign/_version.py
pyalign/cpu.py
pyalign/gaps.py
pyalign/solve.py
pyalign/tests/test_sw.py
pyalign/tests/test_wsb.py
pyalign/tests/__init__.py
pyalign/tests/test_nw.py
pyalign/tests/test_gotoh.py
pyalign/tests/test_batch.py
pyalign/algorithm/__init__.py
pyalign/algorithm/intel_avx2/algorithm.cpython-37m-x86_64-linux-gnu.so
pyalign/algorithm/generic/algorithm.cpython-37m-x86_64-linux-gnu.so
pyalign/problems/factory.py
pyalign/problems/__init__.py
pyalign/problems/instance.py
pyalign/problems/function.py
pyalign/io/alignment.py
pyalign/io/__init__.py
pyalign/io/plot.py
