Metadata-Version: 2.1
Name: pyalign
Version: 0.4.4
Summary: Fast and Versatile Alignments for Python
Author: Bernhard Liebl
Author-email: liebl@informatik.uni-leipzig.de
License: MIT
Requires-Python: >=3.7
License-File: LICENSE
Requires-Dist: numpy (~=1.19)
Requires-Dist: pybind11 (~=2.6.2)
Requires-Dist: cached-property
Requires-Dist: py-cpuinfo (==8.0.0)
Requires-Dist: pymorton (==1.0.5)
Requires-Dist: pyyaml (==6.0)
Requires-Dist: cpufeature (==0.2.0)
